rspy_utilities-0.1.1.dist-info/METADATA
rspy_utilities-0.1.1.dist-info/WHEEL
rspy_utilities/__init__.py
rspy_utilities/_rspy_utilities.py
rspy_utilities/py.typed
rspy_utilities/_rspy_utilities.pyi
rspy_utilities/_rspy_utilities.cpython-38-s390x-linux-gnu.so
rspy_utilities-0.1.1.dist-info/RECORD
