Metadata-Version: 2.4
Name: rspy_utilities
Version: 0.1.1
Classifier: Programming Language :: Rust
Classifier: Programming Language :: Python :: Implementation :: CPython
Requires-Dist: maturin
Requires-Python: >=3.8
